sprockets.clients.dynamodb-0.3.2-py3.5-nspkg.pth
sprockets/clients/dynamodb/__init__.py
sprockets/clients/dynamodb/connector.py
sprockets/clients/dynamodb/exceptions.py
sprockets/clients/dynamodb/utils.py
sprockets.clients.dynamodb-0.3.2.dist-info/DESCRIPTION.rst
sprockets.clients.dynamodb-0.3.2.dist-info/METADATA
sprockets.clients.dynamodb-0.3.2.dist-info/RECORD
sprockets.clients.dynamodb-0.3.2.dist-info/WHEEL
sprockets.clients.dynamodb-0.3.2.dist-info/metadata.json
sprockets.clients.dynamodb-0.3.2.dist-info/namespace_packages.txt
sprockets.clients.dynamodb-0.3.2.dist-info/top_level.txt
sprockets.clients.dynamodb-0.3.2.dist-info/zip-safe
